atklite.py
atklite-1.1.5.dist-info/LICENSE
atklite-1.1.5.dist-info/METADATA
atklite-1.1.5.dist-info/WHEEL
atklite-1.1.5.dist-info/entry_points.txt
atklite-1.1.5.dist-info/top_level.txt
atklite-1.1.5.dist-info/RECORD
