Metadata-Version: 2.1
Name: atklite
Version: 1.1.5
Summary: Library to simplify process of gathering identifiable attributes about files.
Author-email: James Pleger <jpleger@gmail.com>, Darren Spruell <phatbuckett@gmail.com>
Project-URL: Homepage, https://github.com/jpleger/atklite
Classifier: Development Status :: 4 - Beta
Classifier: Environment :: Console
Classifier: Intended Audience :: Information Technology
Classifier: License :: OSI Approved :: BSD License
Classifier: Operating System :: POSIX
Classifier: Programming Language :: Python :: 3
Classifier: Topic :: Security
Classifier: Topic :: Utilities
License-File: LICENSE
Requires-Dist: dnspython
Requires-Dist: python-magic
Requires-Dist: ssdeep
